tangermeme/__init__.py
tangermeme/ablate.py
tangermeme/annotate.py
tangermeme/deep_lift_shap.py
tangermeme/design.py
tangermeme/ersatz.py
tangermeme/io.py
tangermeme/kmers.py
tangermeme/marginalize.py
tangermeme/match.py
tangermeme/pisa.py
tangermeme/plot.py
tangermeme/predict.py
tangermeme/product.py
tangermeme/saturation_mutagenesis.py
tangermeme/seqlet.py
tangermeme/space.py
tangermeme/utils.py
tangermeme/variant_effect.py
tangermeme-1.0.2.dist-info/licenses/LICENSE
tangermeme-1.0.2.dist-info/METADATA
tangermeme-1.0.2.dist-info/WHEEL
tangermeme-1.0.2.dist-info/top_level.txt
tangermeme-1.0.2.dist-info/RECORD
