Metadata-Version: 2.4
Name: tangermeme
Version: 1.0.2
Summary: Biological sequence analysis for the modern age.
Home-page: https://github.com/jmschrei/tangermeme
Author: Jacob Schreiber
Author-email: jmschreiber91@gmail.com
License: LICENSE.txt
License-File: LICENSE
Requires-Dist: numpy<=2.0.1,>=1.14.2
Requires-Dist: scipy>=1.0.0
Requires-Dist: pandas>=1.3.3
Requires-Dist: torch>=1.9.0
Requires-Dist: pybigtools
Requires-Dist: pyfaidx>=0.7.2.1
Requires-Dist: tqdm>=4.64.1
Requires-Dist: numba>=0.55.1
Requires-Dist: logomaker
Requires-Dist: joblib>=1.3.2
Requires-Dist: scikit-learn>=1.2.2
Requires-Dist: matplotlib
Requires-Dist: memelite
Dynamic: author
Dynamic: author-email
Dynamic: home-page
Dynamic: license
Dynamic: license-file
Dynamic: requires-dist
Dynamic: summary
